uuidtools.py
uuidtools-0.1.4.dist-info/entry_points.txt
uuidtools-0.1.4.dist-info/WHEEL
uuidtools-0.1.4.dist-info/METADATA
uuidtools-0.1.4.dist-info/RECORD
