Metadata-Version: 2.1
Name: uuidtools
Version: 0.1.4
Summary: Utility for find, extract, exchange and permutate uuids in string and pandas series
License: MIT
Author: Pablo Ruiz
Requires-Python: >=3.6,<4.0
Classifier: License :: OSI Approved :: MIT License
Classifier: Programming Language :: Python :: 3
Classifier: Programming Language :: Python :: 3.10
Classifier: Programming Language :: Python :: 3.6
Classifier: Programming Language :: Python :: 3.7
Classifier: Programming Language :: Python :: 3.8
Classifier: Programming Language :: Python :: 3.9
Requires-Dist: uuid (>=1.30,<2.0)
